txnet/__init__.py
txnet/layers.py
txnet/models.py
txnet-0.1.dist-info/METADATA
txnet-0.1.dist-info/WHEEL
txnet-0.1.dist-info/top_level.txt
txnet-0.1.dist-info/RECORD
