Metadata-Version: 2.1
Name: txnet
Version: 0.1
Summary: Keras inspired pure python neural network library
Home-page: https://github.com/Tarptaeya/txnet
Author: Anmol Gautam
License: UNKNOWN
Platform: UNKNOWN
Classifier: Programming Language :: Python :: 3
Classifier: License :: OSI Approved :: MIT License
Classifier: Operating System :: OS Independent
Requires-Python: >=3.5
Requires-Dist: numpy
